CHANGELOG.rst
LICENSE.txt
MANIFEST.in
README.rst
VERSION.txt
setup.cfg
setup.py
test-requirements.txt
iniget/__init__.py
iniget/cli.py
iniget/dumper.py
iniget/i18n.py
iniget/loader.py
iniget/sifter.py
iniget/test.py
iniget.egg-info/PKG-INFO
iniget.egg-info/SOURCES.txt
iniget.egg-info/dependency_links.txt
iniget.egg-info/entry_points.txt
iniget.egg-info/requires.txt
iniget.egg-info/top_level.txt
iniget.egg-info/zip-safe