Metadata-Version: 1.1
Name: iniget
Version: 0.4.3
Summary: A command-line tool to extract, normalize, and JSONify values from an iniherit-enabled "INI" file.
Home-page: http://github.com/metagriffin/iniget
Author: metagriffin
Author-email: mg.pypi@metagriffin.net
License: GPLv3+
Keywords: ini configuration value extract inherit
Platform: any
Classifier: Development Status :: 4 - Beta
Classifier: Programming Language :: Python
Classifier: Operating System :: OS Independent
Classifier: Natural Language :: English
Classifier: Environment :: Console
Classifier: Topic :: Utilities
Classifier: License :: OSI Approved :: GNU General Public License v3 or later (GPLv3+)
